scrapeproxy/__init__.py
scrapeproxy/_version.py
scrapeproxy/scraper.py
scrapeproxy-0.0.2.dist-info/METADATA
scrapeproxy-0.0.2.dist-info/WHEEL
scrapeproxy-0.0.2.dist-info/top_level.txt
scrapeproxy-0.0.2.dist-info/RECORD
