Metadata-Version: 2.1
Name: scrapeproxy
Version: 0.0.2
Summary: scrapeproxy
Author-email: Tim Rohner <info@timrohner.ch>
Project-URL: Source, https://github.com/leokster
Keywords: scrapeproxy
Classifier: Intended Audience :: Developers
Classifier: License :: OSI Approved :: MIT License
Classifier: Natural Language :: English
Classifier: Programming Language :: Python :: 3
Classifier: Programming Language :: Python :: 3.6
Classifier: Programming Language :: Python :: 3.7
Classifier: Programming Language :: Python :: 3.8
Classifier: Programming Language :: Python :: 3.9
Classifier: Programming Language :: Python :: 3.10
Classifier: Programming Language :: Python :: 3.11
Requires-Dist: Click <=8.1.7,>=7.0
Requires-Dist: aiohttp <=3.9.3,>=3.9.3
Requires-Dist: loguru <=0.7.2,>=0.7.2
Provides-Extra: dev
Requires-Dist: black <=24.1.1,>=21.7b0 ; extra == 'dev'
Requires-Dist: tox <=4.12.1,>=3.14.0 ; extra == 'dev'
Requires-Dist: twine <=5.0.0,>=1.14.0 ; extra == 'dev'
Provides-Extra: optional1
Requires-Dist: Click <=8.1.7,>=7.0 ; extra == 'optional1'
